{
  "replace": false,
  "values": [
    "#forge:crops/carrot",
    {
      "id": "#forge:crops/spinach",
      "required": false
    },
    {
      "id": "#forge:crops/turnip",
      "required": false
    },
    {
      "id": "#forge:vegetables/spinach",
      "required": false
    },
    {
      "id": "#forge:vegetables/turnip",
      "required": false
    },
    {
      "id": "#c:crops/spinach",
      "required": false
    },
    {
      "id": "#c:crops/turnip",
      "required": false
    },
    {
      "id": "#c:vegetables/spinach",
      "required": false
    },
    {
      "id": "#c:vegetables/turnip",
      "required": false
    },
    {
      "id": "miners_delight:cave_carrot",
      "required": false
    },
    {
      "id": "abundant_atmosphere:cave_parsnip",
      "required": false
    }
  ]
}